syntheticfaker/__init__.py
syntheticfaker/integer.py
syntheticfaker/main.py
syntheticfaker/varchar.py
syntheticfaker/data/alcohol.yaml
syntheticfaker/data/color.yaml
syntheticfaker/data/d_accessories.yaml
syntheticfaker/data/d_characters.yaml
syntheticfaker/data/d_clothing.yaml
syntheticfaker/data/d_home.yaml
syntheticfaker/data/d_movies_series.yaml
syntheticfaker/data/d_toys.yaml
syntheticfaker/data/d_toys_collectibles.yaml
syntheticfaker/data/diseases.yaml
syntheticfaker/data/dlr_park_name.yaml
syntheticfaker/data/electronics_brand.yaml
syntheticfaker/data/m_baby_clothing.yaml
syntheticfaker/data/m_boys_clothing.yaml
syntheticfaker/data/m_dining.yaml
syntheticfaker/data/m_girls_clothing.yaml
syntheticfaker/data/m_handbags_wallets.yaml
syntheticfaker/data/m_home_bath_shower.yaml
syntheticfaker/data/m_home_bed.yaml
syntheticfaker/data/m_home_cleaning.yaml
syntheticfaker/data/m_home_kitchen.yaml
syntheticfaker/data/m_home_luggage.yaml
syntheticfaker/data/m_jewelry.yaml
syntheticfaker/data/m_mens_clothing.yaml
syntheticfaker/data/m_mens_shoes.yaml
syntheticfaker/data/m_toys.yaml
syntheticfaker/data/m_womens_clothing.yaml
syntheticfaker/data/m_womens_shoes.yaml
syntheticfaker/data/pet_supplies.yaml
syntheticfaker/data/pharma_company.yaml
syntheticfaker/data/pharma_drugs.yaml
syntheticfaker/data/pharma_medicines.yaml
syntheticfaker/data/restaurant_names.yaml
syntheticfaker/data/shoe_brand.yaml
syntheticfaker/data/shoe_name.yaml
syntheticfaker/data/songs.yaml
syntheticfaker/data/wdw_entertainment_name.yaml
syntheticfaker/data/wdw_park_name.yaml
syntheticfaker-1.0.7.dist-info/METADATA
syntheticfaker-1.0.7.dist-info/WHEEL
syntheticfaker-1.0.7.dist-info/top_level.txt
syntheticfaker-1.0.7.dist-info/RECORD
