Metadata-Version: 2.1
Name: syntheticfaker
Version: 1.0.7
Summary: A Synthetic Data Generation Python package
Home-page: https://github.com/dominic12/synthetic_faker
Author: Ninad Magdum
Author-email: ninadmagdum13@gmail.com
License: BSD 2-clause
Platform: UNKNOWN
Classifier: Development Status :: 1 - Planning
Classifier: Intended Audience :: Science/Research
Classifier: License :: OSI Approved :: BSD License
Classifier: Operating System :: POSIX :: Linux
Classifier: Operating System :: MacOS :: MacOS X
Classifier: Operating System :: Microsoft :: Windows
Classifier: Programming Language :: Python :: 2
Classifier: Programming Language :: Python :: 2.7
Classifier: Programming Language :: Python :: 3
Classifier: Programming Language :: Python :: 3.4
Classifier: Programming Language :: Python :: 3.5
Requires-Dist: faker
Requires-Dist: pandas
